[{"id":1,"userlogin":"admin","password":111111},{"id":2,"userlogin":"vera","password":222222},{"id":1,"userlogin":"Vera111","password":"$2b$10$pbn8yIfoKZGjMTUHnP66/e/dZ3rRepnzt1/KCQj0umnMs5WuABAtm","email":"v.kuzub@gmail.com","passwordmatch":"$2b$10$pbn8yIfoKZGjMTUHnP66/e/dZ3rRepnzt1/KCQj0umnMs5WuABAtm"},{"id":1,"userlogin":"roma","password":"$2b$10$ZYkOLiW7YJJRW0PmNtwqI.tQO/gzBM8zypEPqlhPpFnZjsnpqfwUy","email":"v.kuzub@gmail.com","passwordmatch":"$2b$10$ZYkOLiW7YJJRW0PmNtwqI.tQO/gzBM8zypEPqlhPpFnZjsnpqfwUy"}]